fuse_client/__init__.py
fuse_client/api_client.py
fuse_client/configuration.py
fuse_client/exceptions.py
fuse_client/rest.py
fuse_client/schemas.py
fuse_client/apis/__init__.py
fuse_client/apis/path_to_api.py
fuse_client/apis/tag_to_api.py
fuse_client/apis/paths/__init__.py
fuse_client/apis/paths/v1_accounts_account_id_events.py
fuse_client/apis/paths/v1_accounts_account_id_finance_score.py
fuse_client/apis/paths/v1_entities_entity_id.py
fuse_client/apis/paths/v1_financial_connections_accounts.py
fuse_client/apis/paths/v1_financial_connections_accounts_details.py
fuse_client/apis/paths/v1_financial_connections_accounts_statement.py
fuse_client/apis/paths/v1_financial_connections_asset_report.py
fuse_client/apis/paths/v1_financial_connections_asset_report_create.py
fuse_client/apis/paths/v1_financial_connections_asset_report_refresh.py
fuse_client/apis/paths/v1_financial_connections_balances.py
fuse_client/apis/paths/v1_financial_connections_financial_connection_id.py
fuse_client/apis/paths/v1_financial_connections_financial_connection_id_to_delete.py
fuse_client/apis/paths/v1_financial_connections_institutions_institution_id.py
fuse_client/apis/paths/v1_financial_connections_institutions_recommended.py
fuse_client/apis/paths/v1_financial_connections_institutions_search.py
fuse_client/apis/paths/v1_financial_connections_institutions_select.py
fuse_client/apis/paths/v1_financial_connections_investments_holdings.py
fuse_client/apis/paths/v1_financial_connections_investments_transactions.py
fuse_client/apis/paths/v1_financial_connections_liabilities.py
fuse_client/apis/paths/v1_financial_connections_migrate.py
fuse_client/apis/paths/v1_financial_connections_owners.py
fuse_client/apis/paths/v1_financial_connections_public_token_exchange.py
fuse_client/apis/paths/v1_financial_connections_sync.py
fuse_client/apis/paths/v1_financial_connections_transactions.py
fuse_client/apis/paths/v1_link_token.py
fuse_client/apis/paths/v1_risk_report_consumer.py
fuse_client-2.0.3.dist-info/LICENSE
fuse_client-2.0.3.dist-info/METADATA
fuse_client-2.0.3.dist-info/WHEEL
fuse_client-2.0.3.dist-info/top_level.txt
fuse_client-2.0.3.dist-info/RECORD
