Metadata-Version: 2.1
Name: fuse-client
Version: 2.0.3
Summary: Fuse
Home-page: 
Author: OpenAPI Generator community
Author-email: team@openapitools.org
Keywords: OpenAPI,OpenAPI-Generator,Fuse
Requires-Python: >=3.7
License-File: LICENSE
Requires-Dist: certifi (>=14.5.14)
Requires-Dist: frozendict (~=2.3.4)
Requires-Dist: python-dateutil (~=2.8.0)
Requires-Dist: setuptools (>=21.0.0)
Requires-Dist: typing-extensions (<5.0.0,>=4.3.0)
Requires-Dist: urllib3 (~=1.26.7)
